AbsalomReckoningConverter/__init__.py
AbsalomReckoningConverter/__main__.py
AbsalomReckoningConverter/arconverter.py
AbsalomReckoningConverter/ardate.py
AbsalomReckoningConverter/constants.py
absalomreckoningconverter-1.0.1.dist-info/METADATA
absalomreckoningconverter-1.0.1.dist-info/WHEEL
absalomreckoningconverter-1.0.1.dist-info/licenses/LICENSE.md
absalomreckoningconverter-1.0.1.dist-info/RECORD
