Metadata-Version: 2.4
Name: AbsalomReckoningConverter
Version: 1.0.1
Summary: Convert from the current or given Gregorian date to Absalom Reckoning from Paizo's Pathfinder RPG
Project-URL: Homepage, https://github.com/cantis/AbsalomReconingConverter
Project-URL: Repository, https://github.com/cantis/AbsalomReconingConverter
Project-URL: Issues, https://github.com/cantis/AbsalomReconingConverter/issues
Author-email: Evan Young <cantis@gmail.com>
Maintainer-email: Evan Young <cantis@gmail.com>
License: Copyright 2025 Evan Young
License-File: LICENSE.md
Keywords: Absalom,Date,Golarion,Pathfinder,RPG,python
Classifier: Intended Audience :: Developers
Classifier: License :: OSI Approved :: MIT License
Classifier: Operating System :: OS Independent
Classifier: Programming Language :: Python :: 3
Classifier: Topic :: Games/Entertainment :: Role-Playing
Classifier: Topic :: Software Development :: Libraries :: Python Modules
Requires-Python: >=3.10
